netCDF4_enhancement/__init__.py
netCDF4_enhancement/netCDF4_enhancement.py
tests/__init__.py
tests/test_netcdf4_streamer.py
netCDF4_enhancement-0.1.2.dist-info/LICENSE.md
netCDF4_enhancement-0.1.2.dist-info/METADATA
netCDF4_enhancement-0.1.2.dist-info/WHEEL
netCDF4_enhancement-0.1.2.dist-info/top_level.txt
netCDF4_enhancement-0.1.2.dist-info/RECORD
