Metadata-Version: 2.1
Name: netCDF4-enhancement
Version: 0.1.2
Summary: Extends the default NetCDF4 driver by providing helpful functionality like reading and writing to variable in some chunks or dealing with variables regardless of its dimension order. Principally directly extends netCDF4 Dataset class with new functionality. Covers most of the functionality that is often the only reason why developers choose to use stogy libraries like xarray.
Home-page: https://github.com/david-salac/NetCDF4-variable-streamer
Author: David Salac
Author-email: info@davidsalac.eu
License: UNKNOWN
Platform: UNKNOWN
Classifier: Programming Language :: Python :: 3
Classifier: License :: OSI Approved :: MIT License
Classifier: Operating System :: OS Independent
Requires-Python: >=3.6
Requires-Dist: numpy
Requires-Dist: netCDF4
